[
  [
    {
    "label":"A propos du Mutualāb",
    "url":"mutualab-lille.html"
    },
    {
    "label":"Wiki Mutualāb",
    "url":"http://wiki.mutualab.org/"
    },

    {
    "label":"Restauration Bis2fly",
    "url":"restaurant-bis2fly.html"
    },

    {
    "label":"Évenements Mutualāb",
    "url":"evenements-mutualab.html"
    },
    "separator",
    {
    "label":"Mentions légales",
    "url":"legal.html"
    }
    
  ],
  [
    {
    "label":"Coworking Lille",
    "url":"http://mutualab.org/"
    },
    {
      "label":"Espace de coworking",
      "url":""
    },
    {
      "label":"Salles de réunions",
      "url":"salle-reunion-lille.html"
    },
    {
      "label":"Maker space",
      "url":"makerspace.html"
    },
    "separator",
    {
      "label":"Reporter un bug",
      "url":"https://github.com/Mutualab/mutualab.org/issues"
    },
    {
      "label":"Contribuer au site",
      "url":"https://github.com/Mutualab/mutualab.org#contribuer"
    }
  ]
]
